pyBrNews/__init__.py
pyBrNews/comments/__init__.py
pyBrNews/comments/crawler.py
pyBrNews/comments/folha_sp.py
pyBrNews/comments/g1.py
pyBrNews/config/__init__.py
pyBrNews/config/database.py
pyBrNews/config/g1_api.py
pyBrNews/news/__init__.py
pyBrNews/news/crawler.py
pyBrNews/news/exame.py
pyBrNews/news/folha_sp.py
pyBrNews/news/g1.py
pyBrNews-0.1.2.dist-info/LICENSE
pyBrNews-0.1.2.dist-info/METADATA
pyBrNews-0.1.2.dist-info/WHEEL
pyBrNews-0.1.2.dist-info/top_level.txt
pyBrNews-0.1.2.dist-info/RECORD
