Metadata-Version: 2.1
Name: pyBrNews
Version: 0.1.2
Summary: A Brazilian News Website Data Acquisition Library for Python
Home-page: https://www.github.com/NepZR/pyBrNews/
Author: Lucas Darlindo Freitas Rodrigues
Author-email: lucas.darlindo@gmail.com
License: GNU GPLv3
Classifier: Development Status :: 4 - Beta
Classifier: Environment :: Console
Classifier: Framework :: IPython
Classifier: Framework :: Jupyter
Classifier: Framework :: Jupyter :: JupyterLab
Classifier: Intended Audience :: Developers
Classifier: Intended Audience :: Education
Classifier: Intended Audience :: Information Technology
Classifier: License :: OSI Approved :: GNU General Public License v3 (GPLv3)
Classifier: Natural Language :: English
Classifier: Natural Language :: Portuguese (Brazilian)
Classifier: Operating System :: OS Independent
Classifier: Programming Language :: Python :: 3.6
Classifier: Programming Language :: Python :: 3.7
Classifier: Programming Language :: Python :: 3.8
Classifier: Programming Language :: Python :: 3.9
Classifier: Programming Language :: Python :: 3.10
Classifier: Topic :: Database
Classifier: Topic :: Education
Classifier: Topic :: Internet
Classifier: Topic :: Internet :: WWW/HTTP
Classifier: Topic :: Scientific/Engineering
Classifier: Topic :: Software Development :: Libraries
Classifier: Topic :: Software Development :: Version Control :: Git
Classifier: Topic :: Text Processing
Classifier: Topic :: Text Processing :: Markup :: HTML
Classifier: Topic :: Text Processing :: Markup :: XML
License-File: LICENSE
Requires-Dist: loguru (>=0.6.0)
Requires-Dist: pymongo (>=4.3.2)
Requires-Dist: requests-html (>=0.10.0)
